AUTHORS
ChangeLog
LICENSE.txt
README.md
requirements.txt
setup.cfg
setup.py
examples/test_bounded_field.py
examples/test_cartesian_mesh.py
examples/test_field.py
examples/test_interp.py
examples/test_io_vtk_2d.py
examples/test_io_vtk_3d.py
maui/__init__.py
maui.egg-info/PKG-INFO
maui.egg-info/SOURCES.txt
maui.egg-info/dependency_links.txt
maui.egg-info/not-zip-safe
maui.egg-info/pbr.json
maui.egg-info/requires.txt
maui.egg-info/top_level.txt
maui/backend/__init__.py
maui/backend/mpi/__init__.py
maui/backend/mpi/array.py
maui/backend/mpi/context.py
maui/backend/mpi/data.py
maui/backend/mpi/domain.py
maui/backend/mpi/halo.py
maui/backend/mpi/index.py
maui/backend/mpi/partition.py
maui/backend/prototypes/__init__.py
maui/backend/prototypes/array.py
maui/backend/prototypes/context.py
maui/backend/prototypes/fd.py
maui/backend/prototypes/helper.py
maui/backend/serial/__init__.py
maui/backend/serial/array.py
maui/backend/serial/context.py
maui/backend/serial/data.py
maui/backend/serial/domain.py
maui/backend/serial/halo.py
maui/backend/serial/index.py
maui/backend/serial/partition.py
maui/field/__init__.py
maui/field/field.py
maui/field/scalar.py
maui/field/view.py
maui/io/__init__.py
maui/io/vtk/__init__.py
maui/io/vtk/encoder.py
maui/io/vtk/helper.py
maui/io/vtk/output.py
maui/io/vtk/vtkdefs.py
maui/io/vtk/writer.py
maui/mesh/__init__.py
maui/mesh/cartesian.py
maui/mesh/curvilinear.py
maui/mesh/helper.py
maui/mesh/rectangular.py
maui/mesh/rectilinear.py
maui/mesh/unstructured.py
maui/mesh/prototypes/__init__.py
maui/mesh/prototypes/mesh.py