Metadata-Version: 1.1
Name: maui
Version: 17.5.8
Summary: Scientific PGAS Framework with IO
Home-page: https://github.com/cstatz/maui
Author: Christoph Statz
Author-email: christoph.statz@tu-dresden.de
License: BSD-3-Clause
Platform: UNKNOWN
Classifier: Development Status :: 3 - Alpha
Classifier: Environment :: Console
Classifier: Intended Audience :: Developers
Classifier: Intended Audience :: Science/Research
Classifier: License :: OSI Approved :: BSD License
Classifier: Operating System :: OS Independent
Classifier: Programming Language :: Python
Classifier: Topic :: Scientific/Engineering :: Mathematics
Classifier: Topic :: Scientific/Engineering :: Physics
Classifier: Natural Language :: English
